<?xml version="1.0"?>

<!-- Copyright (c) 2025 Josh Davidson (Octal450) -->

<PropertyList>
	
	<path>screenselector.ac</path>
	
	<animation>
		<name>Panel lighting</name>
		<type>material</type>
		<object-name>brt.1.integ</object-name>
		<object-name>brt.2.integ</object-name>
		<object-name>brt.3.integ</object-name>
		<object-name>brt.4.integ</object-name>
		<object-name>brt.5.integ</object-name>
		<object-name>brt.6.integ</object-name>
		<object-name>Labels</object-name>
		<object-name>Labels.btn</object-name>
		<emission>
			<red>1.0</red>
			<green>0.85</green>
			<blue>0.6</blue>
			<factor-prop>systems/lighting/main-integ</factor-prop>
		</emission>
	</animation>
	
	<effect>
		<inherits-from>Effects/model-transparent</inherits-from>
		<object-name>Labels</object-name>
	</effect>
    
	<!-- Right now, only 0 and 1 are supported due to the display shaders -->
	<animation>
		<type>knob</type>
		<object-name>brt.1.integ</object-name>
		<object-name>brt.1.knob</object-name>
		<property>controls/cockpit/screensel/du1-dimmer</property>
		<factor>-320</factor>
		<axis>
			<x>0</x>
			<y>0</y>
			<z>1</z>
		</axis>
		<center>
			<x-m>-0.01819</x-m>
			<y-m>-0.03374</y-m>
			<z-m>0.01089</z-m>
		</center>
		<action>
			<binding>
				<command>property-adjust</command>
				<property>instrumentation/du/du1-dimmer</property>
				<factor>1</factor>
				<min>0</min>
				<max>1</max>
				<wrap>false</wrap>
			</binding>
		</action>
	</animation>
	
	<animation>
		<type>knob</type>
		<object-name>brt.2.integ</object-name>
		<object-name>brt.2.knob</object-name>
		<property>controls/cockpit/screensel/du2-dimmer</property>
		<factor>-320</factor>
		<axis>
			<x>0</x>
			<y>0</y>
			<z>1</z>
		</axis>
		<center>
			<x-m>-0.01819</x-m>
			<y-m>-0.02011</y-m>
			<z-m>0.01089</z-m>
		</center>
		<action>
			<binding>
				<command>property-adjust</command>
				<property>instrumentation/du/du2-dimmer</property>
				<factor>1</factor>
				<min>0</min>
				<max>1</max>
				<wrap>false</wrap>
			</binding>
		</action>
	</animation>
	
	<animation>
		<type>knob</type>
		<object-name>brt.3.integ</object-name>
		<object-name>brt.3.knob</object-name>
		<property>controls/cockpit/screensel/du3-dimmer</property>
		<factor>-320</factor>
		<axis>
			<x>0</x>
			<y>0</y>
			<z>1</z>
		</axis>
		<center>
			<x-m>-0.01819</x-m>
			<y-m>-0.00616</y-m>
			<z-m>0.01089</z-m>
		</center>
		<action>
			<binding>
				<command>property-adjust</command>
				<property>instrumentation/du/du3-dimmer</property>
				<factor>1</factor>
				<min>0</min>
				<max>1</max>
				<wrap>false</wrap>
			</binding>
		</action>
	</animation>
	
	<animation>
		<type>knob</type>
		<object-name>brt.4.integ</object-name>
		<object-name>brt.4.knob</object-name>
		<property>controls/cockpit/screensel/du4-dimmer</property>
		<factor>-320</factor>
		<axis>
			<x>0</x>
			<y>0</y>
			<z>1</z>
		</axis>
		<center>
			<x-m>-0.01819</x-m>
			<y-m>0.00759</y-m>
			<z-m>0.01089</z-m>
		</center>
		<action>
			<binding>
				<command>property-adjust</command>
				<property>instrumentation/du/du4-dimmer</property>
				<factor>1</factor>
				<min>0</min>
				<max>1</max>
				<wrap>false</wrap>
			</binding>
		</action>
	</animation>
	
	<animation>
		<type>knob</type>
		<object-name>brt.5.integ</object-name>
		<object-name>brt.5.knob</object-name>
		<property>controls/cockpit/screensel/du5-dimmer</property>
		<factor>-320</factor>
		<axis>
			<x>0</x>
			<y>0</y>
			<z>1</z>
		</axis>
		<center>
			<x-m>-0.01819</x-m>
			<y-m>0.02241</y-m>
			<z-m>0.01089</z-m>
		</center>
		<action>
			<binding>
				<command>property-adjust</command>
				<property>instrumentation/du/du5-dimmer</property>
				<factor>1</factor>
				<min>0</min>
				<max>1</max>
				<wrap>false</wrap>
			</binding>
		</action>
	</animation>
	
	<animation>
		<type>knob</type>
		<object-name>brt.6.integ</object-name>
		<object-name>brt.6.knob</object-name>
		<property>controls/cockpit/screensel/du6-dimmer</property>
		<factor>-320</factor>
		<axis>
			<x>0</x>
			<y>0</y>
			<z>1</z>
		</axis>
		<center>
			<x-m>-0.01819</x-m>
			<y-m>0.0365</y-m>
			<z-m>0.01089</z-m>
		</center>
		<action>
			<binding>
				<command>property-adjust</command>
				<property>instrumentation/du/du6-dimmer</property>
				<factor>1</factor>
				<min>0</min>
				<max>1</max>
				<wrap>false</wrap>
			</binding>
		</action>
	</animation>
	
	<animation>
		<type>pick</type>
		<object-name>config.btn</object-name>
		<action>
			<button>0</button>
			<binding>
				<command>nasal</command>
				<script>
					systems.DUController.setSdPage("CONFIG");
					libraries.Sound.btn2();
				</script>
			</binding>
			<binding>
				<command>property-assign</command>
				<property>controls/cockpit/screensel/config</property>
				<value>1</value>
			</binding>
			<mod-up>
				<binding>
					<command>property-assign</command>
					<property>controls/cockpit/screensel/config</property>
					<value>0</value>
				</binding>
			</mod-up>
		</action>
	</animation>
	<animation>
		<type>translate</type>
		<object-name>config.btn</object-name>
		<object-name>config.label</object-name>
		<property>controls/cockpit/screensel/config</property>
		<factor>-0.001</factor>
		<axis>
			<x>0</x>
			<y>0</y>
			<z>1</z>
		</axis>
	</animation>
	
	<animation>
		<type>pick</type>
		<object-name>conseq.btn</object-name>
		<action>
			<button>0</button>
			<binding>
				<command>nasal</command>
				<script>
					systems.DUController.setSdPage("CONSEQ");
					libraries.Sound.btn2();
				</script>
			</binding>
			<binding>
				<command>property-assign</command>
				<property>controls/cockpit/screensel/conseq</property>
				<value>1</value>
			</binding>
			<mod-up>
				<binding>
					<command>property-assign</command>
					<property>controls/cockpit/screensel/conseq</property>
					<value>0</value>
				</binding>
			</mod-up>
		</action>
	</animation>
	<animation>
		<type>translate</type>
		<object-name>conseq.btn</object-name>
		<object-name>conseq.label</object-name>
		<property>controls/cockpit/screensel/conseq</property>
		<factor>-0.001</factor>
		<axis>
			<x>0</x>
			<y>0</y>
			<z>1</z>
		</axis>
	</animation>
	
	<animation>
		<type>pick</type>
		<object-name>eng.btn</object-name>
		<action>
			<button>0</button>
			<binding>
				<command>nasal</command>
				<script>
					systems.DUController.setSdPage("ENG");
					libraries.Sound.btn2();
				</script>
			</binding>
			<binding>
				<command>property-assign</command>
				<property>controls/cockpit/screensel/eng</property>
				<value>1</value>
			</binding>
			<mod-up>
				<binding>
					<command>property-assign</command>
					<property>controls/cockpit/screensel/eng</property>
					<value>0</value>
				</binding>
			</mod-up>
		</action>
	</animation>
	<animation>
		<type>translate</type>
		<object-name>eng.btn</object-name>
		<object-name>eng.label</object-name>
		<property>controls/cockpit/screensel/eng</property>
		<factor>-0.001</factor>
		<axis>
			<x>0</x>
			<y>0</y>
			<z>1</z>
		</axis>
	</animation>
	
	<animation>
		<type>pick</type>
		<object-name>hyd.btn</object-name>
		<action>
			<button>0</button>
			<binding>
				<command>nasal</command>
				<script>
					systems.DUController.setSdPage("HYD");
					libraries.Sound.btn2();
				</script>
			</binding>
			<binding>
				<command>property-assign</command>
				<property>controls/cockpit/screensel/hyd</property>
				<value>1</value>
			</binding>
			<mod-up>
				<binding>
					<command>property-assign</command>
					<property>controls/cockpit/screensel/hyd</property>
					<value>0</value>
				</binding>
			</mod-up>
		</action>
	</animation>
	<animation>
		<type>translate</type>
		<object-name>hyd.btn</object-name>
		<object-name>hyd.label</object-name>
		<property>controls/cockpit/screensel/hyd</property>
		<factor>-0.001</factor>
		<axis>
			<x>0</x>
			<y>0</y>
			<z>1</z>
		</axis>
	</animation>
	
	<animation>
		<type>pick</type>
		<object-name>misc.btn</object-name>
		<action>
			<button>0</button>
			<binding>
				<command>nasal</command>
				<script>
					systems.DUController.setSdPage("MISC");
					libraries.Sound.btn2();
				</script>
			</binding>
			<binding>
				<command>property-assign</command>
				<property>controls/cockpit/screensel/misc</property>
				<value>1</value>
			</binding>
			<mod-up>
				<binding>
					<command>property-assign</command>
					<property>controls/cockpit/screensel/misc</property>
					<value>0</value>
				</binding>
			</mod-up>
		</action>
	</animation>
	<animation>
		<type>translate</type>
		<object-name>misc.btn</object-name>
		<object-name>misc.label</object-name>
		<property>controls/cockpit/screensel/misc</property>
		<factor>-0.001</factor>
		<axis>
			<x>0</x>
			<y>0</y>
			<z>1</z>
		</axis>
	</animation>
	
	<animation>
		<type>pick</type>
		<object-name>status.btn</object-name>
		<action>
			<button>0</button>
			<binding>
				<command>nasal</command>
				<script>
					systems.DUController.setSdPage("STATUS");
					libraries.Sound.btn2();
				</script>
			</binding>
			<binding>
				<command>property-assign</command>
				<property>controls/cockpit/screensel/status</property>
				<value>1</value>
			</binding>
			<mod-up>
				<binding>
					<command>property-assign</command>
					<property>controls/cockpit/screensel/status</property>
					<value>0</value>
				</binding>
			</mod-up>
		</action>
	</animation>
	<animation>
		<type>translate</type>
		<object-name>status.btn</object-name>
		<object-name>status.label</object-name>
		<property>controls/cockpit/screensel/status</property>
		<factor>-0.001</factor>
		<axis>
			<x>0</x>
			<y>0</y>
			<z>1</z>
		</axis>
	</animation>

</PropertyList>
