<?xml version="1.0" encoding="UTF-8" ?>

<!--
########################################
# Copyright (c) MD-11 Development Team #
########################################
-->

<PropertyList>

	<path>landing.ac</path>

	<animation>
		<name>On/off</name>
		<type>select</type>
		<condition>
			<equals>
				<property>gear/gear[0]/position-norm</property>
				<value>1</value>
			</equals>
		</condition>
	</animation>
	<animation>
		<type>light</type>
		<light-type>spot</light-type>
		<object-name>Cone</object-name>
		<nopreview />
		<position>
			<x>0</x>
			<y>0</y>
			<z>0</z>
		</position>
		<direction>
			<x>-1</x>
			<y>0</y>
			<z>0</z>
		</direction>
		<ambient>
			<r>0.5</r>
			<g>0.5</g>
			<b>0.5</b>
			<a>0.1</a>
		</ambient>
		<diffuse>
			<r>0.7</r>
			<g>0.7</g>
			<b>0.6</b>
			<a>1.0</a>
		</diffuse>
		<specular>
			<r>0.7</r>
			<g>0.7</g>
			<b>0.7</b>
			<a>1.0</a>
		</specular>
		<attenuation>
			<c>1.0</c>
			<l>0.002</l>
			<q>0.00005</q>
		</attenuation>
		<exponent>30.0</exponent>
		<near-m>15</near-m>
		<far-m>1500</far-m>
		<cutoff>2000</cutoff>
	</animation>


</PropertyList>
